{
  "slug": "body-labs",
  "name": "Body Labs",
  "product_url": "",
  "description": "software company acquired by Amazon",
  "product_type": "other",
  "category": "ai-app",
  "status": "active",
  "meta": {
    "added_date": "2026-02-13",
    "last_updated": "2026-02-13",
    "provenance": {
      "name": {
        "source": "wikidata",
        "tier": 1,
        "confidence": 0.95,
        "updated_at": "2026-02-13"
      },
      "description": {
        "source": "wikidata",
        "tier": 1,
        "confidence": 0.95,
        "updated_at": "2026-02-13"
      },
      "product_type": {
        "source": "wikidata",
        "tier": 1,
        "confidence": 0.95,
        "updated_at": "2026-02-13"
      },
      "category": {
        "source": "wikidata",
        "tier": 1,
        "confidence": 0.95,
        "updated_at": "2026-02-13"
      },
      "status": {
        "source": "wikidata",
        "tier": 1,
        "confidence": 0.95,
        "updated_at": "2026-02-13"
      },
      "company.name": {
        "source": "wikidata",
        "tier": 1,
        "confidence": 0.95,
        "updated_at": "2026-02-13"
      },
      "company.url": {
        "source": "wikidata",
        "tier": 1,
        "confidence": 0.95,
        "updated_at": "2026-02-13"
      },
      "company.wikipedia_url": {
        "source": "wikidata",
        "tier": 1,
        "confidence": 0.95,
        "updated_at": "2026-02-13"
      },
      "company.founded_year": {
        "source": "wikidata",
        "tier": 1,
        "confidence": 0.95,
        "updated_at": "2026-02-13"
      },
      "company.headquarters": {
        "source": "wikidata",
        "tier": 1,
        "confidence": 0.95,
        "updated_at": "2026-02-13"
      },
      "company.headquarters.city": {
        "source": "wikidata",
        "tier": 1,
        "confidence": 0.95,
        "updated_at": "2026-02-13"
      },
      "company.headquarters.country": {
        "source": "wikidata",
        "tier": 1,
        "confidence": 0.95,
        "updated_at": "2026-02-13"
      },
      "company.headquarters.country_code": {
        "source": "wikidata",
        "tier": 1,
        "confidence": 0.95,
        "updated_at": "2026-02-13"
      }
    }
  },
  "sources": [
    {
      "url": "https://www.wikidata.org/wiki/Q30315155",
      "source_name": "wikidata",
      "scraped_at": "2026-02-13"
    }
  ],
  "company": {
    "name": "Body Labs",
    "url": "https://en.wikipedia.org/wiki/Body_Labs",
    "wikipedia_url": "https://en.wikipedia.org/wiki/Body_Labs",
    "founded_year": 2013,
    "headquarters": {
      "city": "New York City",
      "country": "United States",
      "country_code": "US"
    }
  }
}
